{
  "How many sales happened last year in the first quarter?\n": [
    {
      "userQuestion": "How many sales happened last year in the first quarter?\n"
    }
  ],
  "How many sales happened last year in the second quarter?\n": [
    {
      "userQuestion": "How many sales happened last year in the second quarter?\n"
    }
  ],
  "What is the total number of units sold each month over the past 12 months?\n": [
    {
      "userQuestion": "What is the total number of units sold each month over the past 12 months?\n"
    }
  ],
  "Which month had the highest sales volume in terms of units over the last 3 years?\n": [
    {
      "userQuestion": "Which month had the highest sales volume in terms of units over the last 3 years?\n"
    }
  ],
  "What is the total revenue generated by each product category in the last quarter?\n": [
    {
      "userQuestion": "What is the total revenue generated by each product category in the last quarter?\n"
    }
  ],
  "What was the total sales generated by each unit category in the last quarter?": [
    {
      "userQuestion": "What was the total sales generated by each unit category in the last quarter?"
    }
  ],
  "How many units were sold in each region last year?\n": [
    {
      "userQuestion": "How many units were sold in each region last year?\n"
    }
  ],
  "What was the average unit price for each product category last month?\n": [
    {
      "userQuestion": "What was the average unit price for each product category last month?\n"
    }
  ],
  "how many bikes were sold in the last quarter": [
    {
      "userQuestion": "how many bikes were sold in the last quarter"
    }
  ],
  "What was the average price of units over the last year": [
    {
      "userQuestion": "What was the average price of units over the last year"
    }
  ],
  "How much, net, was sold of bikes and clothing": [
    {
      "userQuestion": "How much, net, was sold of bikes and clothing"
    }
  ],
  "How many times did we sell more than 40000": [
    {
      "userQuestion": "How many times did we sell more than 40000"
    }
  ]
}